{
  "name": "siyuan-plugin-sidebar-memo",
  "author": "WingDr",
  "url": "https://github.com/WingDr/siyuan-plugin-sidebar-memo",
  "version": "0.2.0",
  "minAppVersion": "2.10.0",
  "backends": ["all"],
  "frontends": ["desktop", "desktop-window", "browser-desktop"],
  "displayName": {
    "default": "Sidebar Memo",
    "zh_CN": "侧边备注"
  },
  "description": {
    "default": "Show the memos on the side of editor.",
    "zh_CN": "让备注在编辑器侧边展开显示"
  },
  "readme": {
    "default": "README.md",
    "zh_CN": "README_zh_CN.md"
  },
  "funding": {
    "openCollective": "",
    "patreon": "",
    "github": ""
  }
}
